{
  "updated": "June 14, 2018 @  8:50 AM",
  "source": "https://docs.google.com/spreadsheets/d/e/2PACX-1vR_ggYGhA2KS7Vyo30ImCIIkRK6omm7dD0tiyeR1ytpg2EUpiMRyIT1QniX6vujm3DnV3eRj5pW6-TX/pubhtml",
  "data": [
    {
      "level": "1",
      "row_data": [
        {
          "key": "level",
          "value": "1"
        },
        {
          "key": "proficiency",
          "value": "2"
        },
        {
          "key": "features",
          "value": [
            {
              "key": "biotic_powers",
              "display": "biotic_powers",
              "subclass_progression": null
            },
            {
              "key": "barrier",
              "display": "barrier",
              "subclass_progression": null
            }
          ]
        },
        {
          "key": "barrierTicks",
          "value": "2"
        },
        {
          "key": "cantrips",
          "value": "3"
        },
        {
          "key": "1",
          "value": "3"
        },
        {
          "key": "2",
          "value": "-"
        },
        {
          "key": "3",
          "value": "-"
        },
        {
          "key": "4",
          "value": "-"
        },
        {
          "key": "5",
          "value": "-"
        },
        {
          "key": "numspells",
          "value": "2"
        },
        {
          "key": "spelllevel",
          "value": "1"
        }
      ]
    },
    {
      "level": "2",
      "row_data": [
        {
          "key": "level",
          "value": "2"
        },
        {
          "key": "proficiency",
          "value": "2"
        },
        {
          "key": "features",
          "value": [
            {
              "key": "subclass",
              "display": "subclass",
              "subclass_progression": null
            }
          ]
        },
        {
          "key": "barrierTicks",
          "value": "2"
        },
        {
          "key": "cantrips",
          "value": "3"
        },
        {
          "key": "1",
          "value": "4"
        },
        {
          "key": "2",
          "value": "-"
        },
        {
          "key": "3",
          "value": "-"
        },
        {
          "key": "4",
          "value": "-"
        },
        {
          "key": "5",
          "value": "-"
        },
        {
          "key": "numspells",
          "value": null
        },
        {
          "key": "spelllevel",
          "value": null
        }
      ]
    },
    {
      "level": "3",
      "row_data": [
        {
          "key": "level",
          "value": "3"
        },
        {
          "key": "proficiency",
          "value": "2"
        },
        {
          "key": "features",
          "value": [
            {
              "key": "biotic_powers",
              "display": "biotic_powers",
              "subclass_progression": null
            }
          ]
        },
        {
          "key": "barrierTicks",
          "value": "2"
        },
        {
          "key": "cantrips",
          "value": "3"
        },
        {
          "key": "1",
          "value": "5"
        },
        {
          "key": "2",
          "value": "-"
        },
        {
          "key": "3",
          "value": "-"
        },
        {
          "key": "4",
          "value": "-"
        },
        {
          "key": "5",
          "value": "-"
        },
        {
          "key": "numspells",
          "value": "1"
        },
        {
          "key": "spelllevel",
          "value": "1"
        }
      ]
    },
    {
      "level": "4",
      "row_data": [
        {
          "key": "level",
          "value": "4"
        },
        {
          "key": "proficiency",
          "value": "2"
        },
        {
          "key": "features",
          "value": [
            {
              "key": "ability_score_improvement",
              "display": "ability_score_improvement",
              "subclass_progression": null
            }
          ]
        },
        {
          "key": "barrierTicks",
          "value": "2"
        },
        {
          "key": "cantrips",
          "value": "3"
        },
        {
          "key": "1",
          "value": "6"
        },
        {
          "key": "2",
          "value": "-"
        },
        {
          "key": "3",
          "value": "-"
        },
        {
          "key": "4",
          "value": "-"
        },
        {
          "key": "5",
          "value": "-"
        },
        {
          "key": "numspells",
          "value": null
        },
        {
          "key": "spelllevel",
          "value": null
        }
      ]
    },
    {
      "level": "5",
      "row_data": [
        {
          "key": "level",
          "value": "5"
        },
        {
          "key": "proficiency",
          "value": "3"
        },
        {
          "key": "features",
          "value": [
            {
              "key": "biotic_powers",
              "display": "biotic_powers",
              "subclass_progression": null
            }
          ]
        },
        {
          "key": "barrierTicks",
          "value": "2"
        },
        {
          "key": "cantrips",
          "value": "4"
        },
        {
          "key": "1",
          "value": "6"
        },
        {
          "key": "2",
          "value": "2"
        },
        {
          "key": "3",
          "value": "-"
        },
        {
          "key": "4",
          "value": "-"
        },
        {
          "key": "5",
          "value": "-"
        },
        {
          "key": "numspells",
          "value": "2"
        },
        {
          "key": "spelllevel",
          "value": "2"
        }
      ]
    },
    {
      "level": "6",
      "row_data": [
        {
          "key": "level",
          "value": "6"
        },
        {
          "key": "proficiency",
          "value": "3"
        },
        {
          "key": "features",
          "value": [
            {
              "key": "subclass",
              "display": "subclass",
              "subclass_progression": null
            }
          ]
        },
        {
          "key": "barrierTicks",
          "value": "2"
        },
        {
          "key": "cantrips",
          "value": "4"
        },
        {
          "key": "1",
          "value": "6"
        },
        {
          "key": "2",
          "value": "3"
        },
        {
          "key": "3",
          "value": "-"
        },
        {
          "key": "4",
          "value": "-"
        },
        {
          "key": "5",
          "value": "-"
        },
        {
          "key": "numspells",
          "value": null
        },
        {
          "key": "spelllevel",
          "value": null
        }
      ]
    },
    {
      "level": "7",
      "row_data": [
        {
          "key": "level",
          "value": "7"
        },
        {
          "key": "proficiency",
          "value": "3"
        },
        {
          "key": "features",
          "value": [
            {
              "key": "biotic_powers",
              "display": "biotic_powers",
              "subclass_progression": null
            }
          ]
        },
        {
          "key": "barrierTicks",
          "value": "3"
        },
        {
          "key": "cantrips",
          "value": "4"
        },
        {
          "key": "1",
          "value": "6"
        },
        {
          "key": "2",
          "value": "4"
        },
        {
          "key": "3",
          "value": "-"
        },
        {
          "key": "4",
          "value": "-"
        },
        {
          "key": "5",
          "value": "-"
        },
        {
          "key": "numspells",
          "value": "1"
        },
        {
          "key": "spelllevel",
          "value": "2"
        }
      ]
    },
    {
      "level": "8",
      "row_data": [
        {
          "key": "level",
          "value": "8"
        },
        {
          "key": "proficiency",
          "value": "3"
        },
        {
          "key": "features",
          "value": [
            {
              "key": "ability_score_improvement",
              "display": "ability_score_improvement",
              "subclass_progression": null
            }
          ]
        },
        {
          "key": "barrierTicks",
          "value": "3"
        },
        {
          "key": "cantrips",
          "value": "4"
        },
        {
          "key": "1",
          "value": "6"
        },
        {
          "key": "2",
          "value": "5"
        },
        {
          "key": "3",
          "value": "-"
        },
        {
          "key": "4",
          "value": "-"
        },
        {
          "key": "5",
          "value": "-"
        },
        {
          "key": "numspells",
          "value": null
        },
        {
          "key": "spelllevel",
          "value": null
        }
      ]
    },
    {
      "level": "9",
      "row_data": [
        {
          "key": "level",
          "value": "9"
        },
        {
          "key": "proficiency",
          "value": "4"
        },
        {
          "key": "features",
          "value": [
            {
              "key": "biotic_powers",
              "display": "biotic_powers",
              "subclass_progression": null
            }
          ]
        },
        {
          "key": "barrierTicks",
          "value": "3"
        },
        {
          "key": "cantrips",
          "value": "4"
        },
        {
          "key": "1",
          "value": "6"
        },
        {
          "key": "2",
          "value": "5"
        },
        {
          "key": "3",
          "value": "1"
        },
        {
          "key": "4",
          "value": "-"
        },
        {
          "key": "5",
          "value": "-"
        },
        {
          "key": "numspells",
          "value": "2"
        },
        {
          "key": "spelllevel",
          "value": "3"
        }
      ]
    },
    {
      "level": "10",
      "row_data": [
        {
          "key": "level",
          "value": "10"
        },
        {
          "key": "proficiency",
          "value": "4"
        },
        {
          "key": "features",
          "value": [
            {
              "key": "subclass",
              "display": "subclass",
              "subclass_progression": null
            }
          ]
        },
        {
          "key": "barrierTicks",
          "value": "3"
        },
        {
          "key": "cantrips",
          "value": "4"
        },
        {
          "key": "1",
          "value": "6"
        },
        {
          "key": "2",
          "value": "5"
        },
        {
          "key": "3",
          "value": "2"
        },
        {
          "key": "4",
          "value": "-"
        },
        {
          "key": "5",
          "value": "-"
        },
        {
          "key": "numspells",
          "value": null
        },
        {
          "key": "spelllevel",
          "value": null
        }
      ]
    },
    {
      "level": "11",
      "row_data": [
        {
          "key": "level",
          "value": "11"
        },
        {
          "key": "proficiency",
          "value": "4"
        },
        {
          "key": "features",
          "value": [
            {
              "key": "biotic_powers",
              "display": "biotic_powers",
              "subclass_progression": null
            }
          ]
        },
        {
          "key": "barrierTicks",
          "value": "3"
        },
        {
          "key": "cantrips",
          "value": "4"
        },
        {
          "key": "1",
          "value": "6"
        },
        {
          "key": "2",
          "value": "5"
        },
        {
          "key": "3",
          "value": "3"
        },
        {
          "key": "4",
          "value": "-"
        },
        {
          "key": "5",
          "value": "-"
        },
        {
          "key": "numspells",
          "value": "2"
        },
        {
          "key": "spelllevel",
          "value": "3"
        }
      ]
    },
    {
      "level": "12",
      "row_data": [
        {
          "key": "level",
          "value": "12"
        },
        {
          "key": "proficiency",
          "value": "4"
        },
        {
          "key": "features",
          "value": [
            {
              "key": "ability_score_improvement",
              "display": "ability_score_improvement",
              "subclass_progression": null
            }
          ]
        },
        {
          "key": "barrierTicks",
          "value": "3"
        },
        {
          "key": "cantrips",
          "value": "4"
        },
        {
          "key": "1",
          "value": "6"
        },
        {
          "key": "2",
          "value": "5"
        },
        {
          "key": "3",
          "value": "4"
        },
        {
          "key": "4",
          "value": "-"
        },
        {
          "key": "5",
          "value": "-"
        },
        {
          "key": "numspells",
          "value": null
        },
        {
          "key": "spelllevel",
          "value": null
        }
      ]
    },
    {
      "level": "13",
      "row_data": [
        {
          "key": "level",
          "value": "13"
        },
        {
          "key": "proficiency",
          "value": "5"
        },
        {
          "key": "features",
          "value": [
            {
              "key": "biotic_powers",
              "display": "biotic_powers",
              "subclass_progression": null
            }
          ]
        },
        {
          "key": "barrierTicks",
          "value": "4"
        },
        {
          "key": "cantrips",
          "value": "5"
        },
        {
          "key": "1",
          "value": "6"
        },
        {
          "key": "2",
          "value": "5"
        },
        {
          "key": "3",
          "value": "4"
        },
        {
          "key": "4",
          "value": "-"
        },
        {
          "key": "5",
          "value": "-"
        },
        {
          "key": "numspells",
          "value": "2"
        },
        {
          "key": "spelllevel",
          "value": "4"
        }
      ]
    },
    {
      "level": "14",
      "row_data": [
        {
          "key": "level",
          "value": "14"
        },
        {
          "key": "proficiency",
          "value": "5"
        },
        {
          "key": "features",
          "value": [
            {
              "key": "subclass",
              "display": "subclass",
              "subclass_progression": null
            }
          ]
        },
        {
          "key": "barrierTicks",
          "value": "4"
        },
        {
          "key": "cantrips",
          "value": "5"
        },
        {
          "key": "1",
          "value": "6"
        },
        {
          "key": "2",
          "value": "5"
        },
        {
          "key": "3",
          "value": "4"
        },
        {
          "key": "4",
          "value": "1"
        },
        {
          "key": "5",
          "value": "-"
        },
        {
          "key": "numspells",
          "value": null
        },
        {
          "key": "spelllevel",
          "value": null
        }
      ]
    },
    {
      "level": "15",
      "row_data": [
        {
          "key": "level",
          "value": "15"
        },
        {
          "key": "proficiency",
          "value": "5"
        },
        {
          "key": "features",
          "value": [
            {
              "key": "biotic_powers",
              "display": "biotic_powers",
              "subclass_progression": null
            }
          ]
        },
        {
          "key": "barrierTicks",
          "value": "4"
        },
        {
          "key": "cantrips",
          "value": "5"
        },
        {
          "key": "1",
          "value": "6"
        },
        {
          "key": "2",
          "value": "5"
        },
        {
          "key": "3",
          "value": "4"
        },
        {
          "key": "4",
          "value": "2"
        },
        {
          "key": "5",
          "value": "-"
        },
        {
          "key": "numspells",
          "value": "2"
        },
        {
          "key": "spelllevel",
          "value": "4"
        }
      ]
    },
    {
      "level": "16",
      "row_data": [
        {
          "key": "level",
          "value": "16"
        },
        {
          "key": "proficiency",
          "value": "5"
        },
        {
          "key": "features",
          "value": [
            {
              "key": "ability_score_improvement",
              "display": "ability_score_improvement",
              "subclass_progression": null
            }
          ]
        },
        {
          "key": "barrierTicks",
          "value": "4"
        },
        {
          "key": "cantrips",
          "value": "5"
        },
        {
          "key": "1",
          "value": "6"
        },
        {
          "key": "2",
          "value": "5"
        },
        {
          "key": "3",
          "value": "4"
        },
        {
          "key": "4",
          "value": "2"
        },
        {
          "key": "5",
          "value": "-"
        },
        {
          "key": "numspells",
          "value": null
        },
        {
          "key": "spelllevel",
          "value": null
        }
      ]
    },
    {
      "level": "17",
      "row_data": [
        {
          "key": "level",
          "value": "17"
        },
        {
          "key": "proficiency",
          "value": "6"
        },
        {
          "key": "features",
          "value": [
            {
              "key": "empowered_biotics",
              "display": "empowered_biotics",
              "subclass_progression": null
            }
          ]
        },
        {
          "key": "barrierTicks",
          "value": "4"
        },
        {
          "key": "cantrips",
          "value": "5"
        },
        {
          "key": "1",
          "value": "6"
        },
        {
          "key": "2",
          "value": "5"
        },
        {
          "key": "3",
          "value": "4"
        },
        {
          "key": "4",
          "value": "2"
        },
        {
          "key": "5",
          "value": "1"
        },
        {
          "key": "numspells",
          "value": null
        },
        {
          "key": "spelllevel",
          "value": null
        }
      ]
    },
    {
      "level": "18",
      "row_data": [
        {
          "key": "level",
          "value": "18"
        },
        {
          "key": "proficiency",
          "value": "6"
        },
        {
          "key": "features",
          "value": [
            {
              "key": "biotic_mastery",
              "display": "biotic_mastery",
              "subclass_progression": null
            }
          ]
        },
        {
          "key": "barrierTicks",
          "value": "4"
        },
        {
          "key": "cantrips",
          "value": "5"
        },
        {
          "key": "1",
          "value": "6"
        },
        {
          "key": "2",
          "value": "5"
        },
        {
          "key": "3",
          "value": "4"
        },
        {
          "key": "4",
          "value": "3"
        },
        {
          "key": "5",
          "value": "1"
        },
        {
          "key": "numspells",
          "value": null
        },
        {
          "key": "spelllevel",
          "value": null
        }
      ]
    },
    {
      "level": "19",
      "row_data": [
        {
          "key": "level",
          "value": "19"
        },
        {
          "key": "proficiency",
          "value": "6"
        },
        {
          "key": "features",
          "value": [
            {
              "key": "ability_score_improvement",
              "display": "ability_score_improvement",
              "subclass_progression": null
            }
          ]
        },
        {
          "key": "barrierTicks",
          "value": "5"
        },
        {
          "key": "cantrips",
          "value": "5"
        },
        {
          "key": "1",
          "value": "6"
        },
        {
          "key": "2",
          "value": "5"
        },
        {
          "key": "3",
          "value": "4"
        },
        {
          "key": "4",
          "value": "3"
        },
        {
          "key": "5",
          "value": "2"
        },
        {
          "key": "numspells",
          "value": null
        },
        {
          "key": "spelllevel",
          "value": null
        }
      ]
    },
    {
      "level": "20",
      "row_data": [
        {
          "key": "level",
          "value": "20"
        },
        {
          "key": "proficiency",
          "value": "6"
        },
        {
          "key": "features",
          "value": [
            {
              "key": "signature_biotics",
              "display": "signature_biotics",
              "subclass_progression": null
            }
          ]
        },
        {
          "key": "barrierTicks",
          "value": "5"
        },
        {
          "key": "cantrips",
          "value": "5"
        },
        {
          "key": "1",
          "value": "6"
        },
        {
          "key": "2",
          "value": "5"
        },
        {
          "key": "3",
          "value": "4"
        },
        {
          "key": "4",
          "value": "3"
        },
        {
          "key": "5",
          "value": "3"
        },
        {
          "key": "numspells",
          "value": null
        },
        {
          "key": "spelllevel",
          "value": null
        }
      ]
    }
  ],
  "headers": [
    {
      "display": "Level",
      "spell_header": false
    },
    {
      "display": "Proficiency",
      "spell_header": false
    },
    {
      "display": "Features",
      "spell_header": false
    },
    {
      "display": "Barrier Ticks",
      "spell_header": false
    },
    {
      "display": "Cantrips",
      "spell_header": false
    },
    {
      "display": "1st",
      "spell_header": true
    },
    {
      "display": "2nd",
      "spell_header": true
    },
    {
      "display": "3rd",
      "spell_header": true
    },
    {
      "display": "4th",
      "spell_header": true
    },
    {
      "display": "5th",
      "spell_header": true
    },
    {
      "display": "numSpells",
      "spell_header": false
    },
    {
      "display": "spellLevel",
      "spell_header": false
    }
  ]
}