{
  "updated": "September  6, 2017 @  9:28 AM",
  "source": "https://docs.google.com/spreadsheets/d/e/2PACX-1vTPhVRIodUwbDYFw8wJZtmb63tTjFJMxY-cN6P5nayPpJhNxAQFqIxeSLd5Tz75aOZ7CLuBkNsDrcs9/pubhtml",
  "data": [
    {
      "name": "Alert",
      "not_available": null,
      "page_number": "165",
      "description": null,
      "prerequisite": null,
      "batarian": null,
      "drell": "x",
      "human": "x",
      "quarian": null,
      "salarian": "x",
      "turian": "x"
    },
    {
      "name": "Actor",
      "not_available": null,
      "page_number": "165",
      "description": null,
      "prerequisite": null,
      "batarian": null,
      "drell": "x",
      "human": null,
      "quarian": null,
      "salarian": "x",
      "turian": null
    },
    {
      "name": "Athlete",
      "not_available": null,
      "page_number": "165",
      "description": null,
      "prerequisite": null,
      "batarian": null,
      "drell": null,
      "human": "x",
      "quarian": null,
      "salarian": "x",
      "turian": "x"
    },
    {
      "name": "Biotic Slayer",
      "not_available": null,
      "page_number": "168",
      "description": "See Mage Slayer",
      "prerequisite": null,
      "batarian": "x",
      "drell": null,
      "human": "x",
      "quarian": "x",
      "salarian": "x",
      "turian": "x"
    },
    {
      "name": "Charger",
      "not_available": null,
      "page_number": "165",
      "description": null,
      "prerequisite": null,
      "batarian": "x",
      "drell": null,
      "human": "x",
      "quarian": null,
      "salarian": null,
      "turian": "x"
    },
    {
      "name": "Crossbow Expert",
      "not_available": "x",
      "page_number": "165",
      "description": null,
      "prerequisite": null,
      "batarian": null,
      "drell": null,
      "human": null,
      "quarian": null,
      "salarian": null,
      "turian": null
    },
    {
      "name": "Defensive Duelist",
      "not_available": "x",
      "page_number": "165",
      "description": null,
      "prerequisite": null,
      "batarian": null,
      "drell": null,
      "human": null,
      "quarian": null,
      "salarian": null,
      "turian": null
    },
    {
      "name": "Dual Wielder",
      "not_available": "x",
      "page_number": "165",
      "description": null,
      "prerequisite": null,
      "batarian": null,
      "drell": null,
      "human": null,
      "quarian": null,
      "salarian": null,
      "turian": null
    },
    {
      "name": "Dungeon Delver",
      "not_available": "x",
      "page_number": "166",
      "description": null,
      "prerequisite": null,
      "batarian": null,
      "drell": null,
      "human": null,
      "quarian": null,
      "salarian": null,
      "turian": null
    },
    {
      "name": "Durable",
      "not_available": null,
      "page_number": "166",
      "description": null,
      "prerequisite": null,
      "batarian": "x",
      "drell": null,
      "human": "x",
      "quarian": null,
      "salarian": null,
      "turian": "x"
    },
    {
      "name": "Elemental Adept",
      "not_available": null,
      "page_number": "166",
      "description": null,
      "prerequisite": null,
      "batarian": null,
      "drell": null,
      "human": "x",
      "quarian": null,
      "salarian": null,
      "turian": null
    },
    {
      "name": "Grappler",
      "not_available": null,
      "page_number": "167",
      "description": null,
      "prerequisite": null,
      "batarian": "x",
      "drell": null,
      "human": "x",
      "quarian": null,
      "salarian": null,
      "turian": "x"
    },
    {
      "name": "Great Weapon Master",
      "not_available": "x",
      "page_number": "167",
      "description": null,
      "prerequisite": null,
      "batarian": null,
      "drell": null,
      "human": null,
      "quarian": null,
      "salarian": null,
      "turian": null
    },
    {
      "name": "Grenadier",
      "not_available": null,
      "page_number": "-",
      "description": "-- +2 grenade capacity\n-- When you use a grenade, you may choose to make a ranged weapon attack on a creature instead of choosing a target location. Add your dexterity modifier to the attack roll.\n-- On a hit, the grenade deals 1d4 + dexterity modifier bludgeoning damage to the target and it has disadvantage on the saving throw caused by the grenade. The grenade lands at the target's location.\n-- On a miss, the grenade lands 2m beyond the target.\n-- On a critical miss, roll 2d4. The first die represents the number of spaces away from the target in which the grenade lands. The second die represents the direction (1 = North, 2= East, 3 = South, 4 = West). E.g., 2 & 2, the grenade would land 2 spaces east of the target.\n-- Once the grenade's location is determined, it resolves normally.\n",
      "prerequisite": null,
      "batarian": "x",
      "drell": "x",
      "human": "x",
      "quarian": "x",
      "salarian": "x",
      "turian": "x"
    },
    {
      "name": "Healer",
      "not_available": "x",
      "page_number": "167",
      "description": null,
      "prerequisite": null,
      "batarian": null,
      "drell": null,
      "human": null,
      "quarian": null,
      "salarian": null,
      "turian": null
    },
    {
      "name": "Heavily Armored",
      "not_available": null,
      "page_number": "167",
      "description": null,
      "prerequisite": null,
      "batarian": null,
      "drell": null,
      "human": null,
      "quarian": "x",
      "salarian": null,
      "turian": null
    },
    {
      "name": "Heavy Armor Master",
      "not_available": null,
      "page_number": "167",
      "description": null,
      "prerequisite": null,
      "batarian": "x",
      "drell": "x",
      "human": null,
      "quarian": null,
      "salarian": null,
      "turian": "x"
    },
    {
      "name": "Inspiring Leader",
      "not_available": null,
      "page_number": "167",
      "description": null,
      "prerequisite": null,
      "batarian": null,
      "drell": "x",
      "human": null,
      "quarian": "x",
      "salarian": "x",
      "turian": "x"
    },
    {
      "name": "Keen Mind",
      "not_available": null,
      "page_number": "167",
      "description": null,
      "prerequisite": null,
      "batarian": null,
      "drell": "x",
      "human": null,
      "quarian": "x",
      "salarian": "x",
      "turian": "x"
    },
    {
      "name": "Lightly Armored",
      "not_available": null,
      "page_number": "167",
      "description": null,
      "prerequisite": null,
      "batarian": null,
      "drell": null,
      "human": null,
      "quarian": null,
      "salarian": null,
      "turian": null
    },
    {
      "name": "Linguist",
      "not_available": null,
      "page_number": "167",
      "description": null,
      "prerequisite": null,
      "batarian": null,
      "drell": "x",
      "human": "x",
      "quarian": "x",
      "salarian": "x",
      "turian": null
    },
    {
      "name": "Lucky",
      "not_available": null,
      "page_number": "167",
      "description": null,
      "prerequisite": null,
      "batarian": null,
      "drell": null,
      "human": "x",
      "quarian": null,
      "salarian": null,
      "turian": null
    },
    {
      "name": "Mage Slayer",
      "not_available": "x",
      "page_number": "168",
      "description": null,
      "prerequisite": null,
      "batarian": null,
      "drell": null,
      "human": null,
      "quarian": null,
      "salarian": null,
      "turian": null
    },
    {
      "name": "Magic Initiate",
      "not_available": "x",
      "page_number": "168",
      "description": null,
      "prerequisite": null,
      "batarian": null,
      "drell": null,
      "human": null,
      "quarian": null,
      "salarian": null,
      "turian": null
    },
    {
      "name": "Martial Adept",
      "not_available": "x",
      "page_number": "168",
      "description": null,
      "prerequisite": null,
      "batarian": null,
      "drell": null,
      "human": null,
      "quarian": null,
      "salarian": null,
      "turian": null
    },
    {
      "name": "Medium Armor Master",
      "not_available": null,
      "page_number": "168",
      "description": null,
      "prerequisite": null,
      "batarian": null,
      "drell": null,
      "human": "x",
      "quarian": "x",
      "salarian": null,
      "turian": "x"
    },
    {
      "name": "Mobile",
      "not_available": null,
      "page_number": "168",
      "description": null,
      "prerequisite": null,
      "batarian": null,
      "drell": "x",
      "human": "x",
      "quarian": "x",
      "salarian": "x",
      "turian": "x"
    },
    {
      "name": "Moderately Armored",
      "not_available": null,
      "page_number": "168",
      "description": null,
      "prerequisite": null,
      "batarian": null,
      "drell": "x",
      "human": null,
      "quarian": null,
      "salarian": "x",
      "turian": null
    },
    {
      "name": "Mounted Combat",
      "not_available": "x",
      "page_number": "168",
      "description": null,
      "prerequisite": null,
      "batarian": null,
      "drell": null,
      "human": null,
      "quarian": null,
      "salarian": null,
      "turian": null
    },
    {
      "name": "Observant",
      "not_available": null,
      "page_number": "168",
      "description": null,
      "prerequisite": null,
      "batarian": null,
      "drell": "x",
      "human": "x",
      "quarian": "x",
      "salarian": "x",
      "turian": "x"
    },
    {
      "name": "Polearm Master",
      "not_available": "x",
      "page_number": "168",
      "description": null,
      "prerequisite": null,
      "batarian": null,
      "drell": null,
      "human": null,
      "quarian": null,
      "salarian": null,
      "turian": null
    },
    {
      "name": "Resilient",
      "not_available": null,
      "page_number": "168",
      "description": null,
      "prerequisite": null,
      "batarian": "x",
      "drell": null,
      "human": "x",
      "quarian": null,
      "salarian": null,
      "turian": "x"
    },
    {
      "name": "Ritual Caster",
      "not_available": "x",
      "page_number": "169",
      "description": null,
      "prerequisite": null,
      "batarian": null,
      "drell": null,
      "human": null,
      "quarian": null,
      "salarian": null,
      "turian": null
    },
    {
      "name": "Savage Attacker",
      "not_available": null,
      "page_number": "169",
      "description": null,
      "prerequisite": null,
      "batarian": "x",
      "drell": null,
      "human": "x",
      "quarian": null,
      "salarian": null,
      "turian": "x"
    },
    {
      "name": "Sentinel",
      "not_available": null,
      "page_number": "169",
      "description": null,
      "prerequisite": null,
      "batarian": "x",
      "drell": null,
      "human": "x",
      "quarian": null,
      "salarian": null,
      "turian": "x"
    },
    {
      "name": "Sharpshooter",
      "not_available": null,
      "page_number": "170",
      "description": null,
      "prerequisite": null,
      "batarian": null,
      "drell": null,
      "human": "x",
      "quarian": "x",
      "salarian": "x",
      "turian": "x"
    },
    {
      "name": "Shield Master",
      "not_available": "x",
      "page_number": "170",
      "description": null,
      "prerequisite": null,
      "batarian": null,
      "drell": null,
      "human": null,
      "quarian": null,
      "salarian": null,
      "turian": null
    },
    {
      "name": "Skilled",
      "not_available": null,
      "page_number": "170",
      "description": null,
      "prerequisite": null,
      "batarian": null,
      "drell": null,
      "human": "x",
      "quarian": "x",
      "salarian": "x",
      "turian": "x"
    },
    {
      "name": "Skulker",
      "not_available": null,
      "page_number": "170",
      "description": null,
      "prerequisite": null,
      "batarian": null,
      "drell": "x",
      "human": "x",
      "quarian": null,
      "salarian": "x",
      "turian": null
    },
    {
      "name": "Spell Sniper",
      "not_available": "x",
      "page_number": "170",
      "description": null,
      "prerequisite": null,
      "batarian": null,
      "drell": null,
      "human": null,
      "quarian": null,
      "salarian": null,
      "turian": null
    },
    {
      "name": "Tavern Brawler",
      "not_available": null,
      "page_number": "170",
      "description": null,
      "prerequisite": null,
      "batarian": "x",
      "drell": null,
      "human": "x",
      "quarian": null,
      "salarian": null,
      "turian": "x"
    },
    {
      "name": "Tough",
      "not_available": null,
      "page_number": "170",
      "description": null,
      "prerequisite": null,
      "batarian": "x",
      "drell": null,
      "human": "x",
      "quarian": null,
      "salarian": null,
      "turian": "x"
    },
    {
      "name": "War Caster",
      "not_available": null,
      "page_number": "170",
      "description": null,
      "prerequisite": null,
      "batarian": null,
      "drell": null,
      "human": null,
      "quarian": null,
      "salarian": null,
      "turian": null
    },
    {
      "name": "Weapon Master",
      "not_available": null,
      "page_number": "170",
      "description": "Instead of gain proficiency with 4 weapons, you gain proficiency with 2 ranged weapons",
      "prerequisite": null,
      "batarian": "x",
      "drell": null,
      "human": "x",
      "quarian": null,
      "salarian": null,
      "turian": "x"
    }
  ]
}